{".class": "MypyFile", "_fullname": "datastructure.graph.union_find", "is_partial_stub_package": false, "is_stub": false, "names": {".class": "SymbolTable", "QuickFind": {".class": "SymbolTableNode", "kind": "Gdef", "node": {".class": "TypeInfo", "_promote": null, "abstract_attributes": [], "bases": ["builtins.object"], "declared_metaclass": null, "defn": {".class": "ClassDef", "fullname": "datastructure.graph.union_find.QuickFind", "name": "QuickFind", "type_vars": []}, "flags": [], "fullname": "datastructure.graph.union_find.QuickFind", "metaclass_type": null, "metadata": {}, "module_name": "datastructure.graph.union_find", "mro": ["datastructure.graph.union_find.QuickFind", "builtins.object"], "names": {".class": "SymbolTable", "__init__": {".class": "SymbolTableNode", "kind": "Mdef", "node": {".class": "FuncDef", "arg_kinds": [0, 0], "arg_names": ["self", "N"], "flags": [], "fullname": "datastructure.graph.union_find.QuickFind.__init__", "name": "__init__", "type": {".class": "CallableType", "arg_kinds": [0, 0], "arg_names": ["self", "N"], "arg_types": ["datastructure.graph.union_find.QuickFind", "builtins.int"], "bound_args": [], "def_extras": {"first_arg": "self"}, "fallback": "builtins.function", "implicit": false, "is_ellipsis_args": false, "name": "__init__ of QuickFind", "ret_type": {".class": "NoneType"}, "variables": []}}}, "find": {".class": "SymbolTableNode", "kind": "Mdef", "node": {".class": "FuncDef", "arg_kinds": [0, 0, 0], "arg_names": ["self", "p", "q"], "flags": [], "fullname": "datastructure.graph.union_find.QuickFind.find", "name": "find", "type": {".class": "CallableType", "arg_kinds": [0, 0, 0], "arg_names": ["self", "p", "q"], "arg_types": ["datastructure.graph.union_find.QuickFind", "builtins.int", "builtins.int"], "bound_args": [], "def_extras": {"first_arg": "self"}, "fallback": "builtins.function", "implicit": false, "is_ellipsis_args": false, "name": "find of QuickFind", "ret_type": "builtins.bool", "variables": []}}}, "root_ids": {".class": "SymbolTableNode", "implicit": true, "kind": "Mdef", "node": {".class": "Var", "flags": [], "fullname": "datastructure.graph.union_find.QuickFind.root_ids", "name": "root_ids", "type": {".class": "Instance", "args": ["builtins.int"], "type_ref": "builtins.list"}}}, "union": {".class": "SymbolTableNode", "kind": "Mdef", "node": {".class": "FuncDef", "arg_kinds": [0, 0, 0], "arg_names": ["self", "p", "q"], "flags": [], "fullname": "datastructure.graph.union_find.QuickFind.union", "name": "union", "type": {".class": "CallableType", "arg_kinds": [0, 0, 0], "arg_names": ["self", "p", "q"], "arg_types": ["datastructure.graph.union_find.QuickFind", "builtins.int", "builtins.int"], "bound_args": [], "def_extras": {"first_arg": "self"}, "fallback": "builtins.function", "implicit": false, "is_ellipsis_args": false, "name": "union of QuickFind", "ret_type": {".class": "NoneType"}, "variables": []}}}}, "tuple_type": null, "type_vars": [], "typeddict_type": null}}, "QuickUnion": {".class": "SymbolTableNode", "kind": "Gdef", "node": {".class": "TypeInfo", "_promote": null, "abstract_attributes": [], "bases": ["builtins.object"], "declared_metaclass": null, "defn": {".class": "ClassDef", "fullname": "datastructure.graph.union_find.QuickUnion", "name": "QuickUnion", "type_vars": []}, "flags": [], "fullname": "datastructure.graph.union_find.QuickUnion", "metaclass_type": null, "metadata": {}, "module_name": "datastructure.graph.union_find", "mro": ["datastructure.graph.union_find.QuickUnion", "builtins.object"], "names": {".class": "SymbolTable", "__init__": {".class": "SymbolTableNode", "kind": "Mdef", "node": {".class": "FuncDef", "arg_kinds": [0, 0], "arg_names": ["self", "N"], "flags": [], "fullname": "datastructure.graph.union_find.QuickUnion.__init__", "name": "__init__", "type": {".class": "CallableType", "arg_kinds": [0, 0], "arg_names": ["self", "N"], "arg_types": ["datastructure.graph.union_find.QuickUnion", "builtins.int"], "bound_args": [], "def_extras": {"first_arg": "self"}, "fallback": "builtins.function", "implicit": false, "is_ellipsis_args": false, "name": "__init__ of QuickUnion", "ret_type": {".class": "NoneType"}, "variables": []}}}, "find": {".class": "SymbolTableNode", "kind": "Mdef", "node": {".class": "FuncDef", "arg_kinds": [0, 0, 0], "arg_names": ["self", "p", "q"], "flags": [], "fullname": "datastructure.graph.union_find.QuickUnion.find", "name": "find", "type": {".class": "CallableType", "arg_kinds": [0, 0, 0], "arg_names": ["self", "p", "q"], "arg_types": ["datastructure.graph.union_find.QuickUnion", "builtins.int", "builtins.int"], "bound_args": [], "def_extras": {"first_arg": "self"}, "fallback": "builtins.function", "implicit": false, "is_ellipsis_args": false, "name": "find of QuickUnion", "ret_type": "builtins.bool", "variables": []}}}, "root": {".class": "SymbolTableNode", "kind": "Mdef", "node": {".class": "FuncDef", "arg_kinds": [0, 0], "arg_names": ["self", "i"], "flags": [], "fullname": "datastructure.graph.union_find.QuickUnion.root", "name": "root", "type": {".class": "CallableType", "arg_kinds": [0, 0], "arg_names": ["self", "i"], "arg_types": ["datastructure.graph.union_find.QuickUnion", "builtins.int"], "bound_args": [], "def_extras": {"first_arg": "self"}, "fallback": "builtins.function", "implicit": false, "is_ellipsis_args": false, "name": "root of QuickUnion", "ret_type": "builtins.int", "variables": []}}}, "root_ids": {".class": "SymbolTableNode", "implicit": true, "kind": "Mdef", "node": {".class": "Var", "flags": [], "fullname": "datastructure.graph.union_find.QuickUnion.root_ids", "name": "root_ids", "type": {".class": "Instance", "args": ["builtins.int"], "type_ref": "builtins.list"}}}, "union": {".class": "SymbolTableNode", "kind": "Mdef", "node": {".class": "FuncDef", "arg_kinds": [0, 0, 0], "arg_names": ["self", "p", "q"], "flags": [], "fullname": "datastructure.graph.union_find.QuickUnion.union", "name": "union", "type": {".class": "CallableType", "arg_kinds": [0, 0, 0], "arg_names": ["self", "p", "q"], "arg_types": ["datastructure.graph.union_find.QuickUnion", "builtins.int", "builtins.int"], "bound_args": [], "def_extras": {"first_arg": "self"}, "fallback": "builtins.function", "implicit": false, "is_ellipsis_args": false, "name": "union of QuickUnion", "ret_type": {".class": "NoneType"}, "variables": []}}}}, "tuple_type": null, "type_vars": [], "typeddict_type": null}}, "QuickUnionFirstImprovement": {".class": "SymbolTableNode", "kind": "Gdef", "node": {".class": "TypeInfo", "_promote": null, "abstract_attributes": [], "bases": ["builtins.object"], "declared_metaclass": null, "defn": {".class": "ClassDef", "fullname": "datastructure.graph.union_find.QuickUnionFirstImprovement", "name": "QuickUnionFirstImprovement", "type_vars": []}, "flags": [], "fullname": "datastructure.graph.union_find.QuickUnionFirstImprovement", "metaclass_type": null, "metadata": {}, "module_name": "datastructure.graph.union_find", "mro": ["datastructure.graph.union_find.QuickUnionFirstImprovement", "builtins.object"], "names": {".class": "SymbolTable", "__init__": {".class": "SymbolTableNode", "kind": "Mdef", "node": {".class": "FuncDef", "arg_kinds": [0, 0], "arg_names": ["self", "N"], "flags": [], "fullname": "datastructure.graph.union_find.QuickUnionFirstImprovement.__init__", "name": "__init__", "type": {".class": "CallableType", "arg_kinds": [0, 0], "arg_names": ["self", "N"], "arg_types": ["datastructure.graph.union_find.QuickUnionFirstImprovement", "builtins.int"], "bound_args": [], "def_extras": {"first_arg": "self"}, "fallback": "builtins.function", "implicit": false, "is_ellipsis_args": false, "name": "__init__ of QuickUnionFirstImprovement", "ret_type": {".class": "NoneType"}, "variables": []}}}, "find": {".class": "SymbolTableNode", "kind": "Mdef", "node": {".class": "FuncDef", "arg_kinds": [0, 0, 0], "arg_names": ["self", "p", "q"], "flags": [], "fullname": "datastructure.graph.union_find.QuickUnionFirstImprovement.find", "name": "find", "type": {".class": "CallableType", "arg_kinds": [0, 0, 0], "arg_names": ["self", "p", "q"], "arg_types": ["datastructure.graph.union_find.QuickUnionFirstImprovement", "builtins.int", "builtins.int"], "bound_args": [], "def_extras": {"first_arg": "self"}, "fallback": "builtins.function", "implicit": false, "is_ellipsis_args": false, "name": "find of QuickUnionFirstImprovement", "ret_type": "builtins.bool", "variables": []}}}, "root": {".class": "SymbolTableNode", "kind": "Mdef", "node": {".class": "FuncDef", "arg_kinds": [0, 0], "arg_names": ["self", "i"], "flags": [], "fullname": "datastructure.graph.union_find.QuickUnionFirstImprovement.root", "name": "root", "type": {".class": "CallableType", "arg_kinds": [0, 0], "arg_names": ["self", "i"], "arg_types": ["datastructure.graph.union_find.QuickUnionFirstImprovement", "builtins.int"], "bound_args": [], "def_extras": {"first_arg": "self"}, "fallback": "builtins.function", "implicit": false, "is_ellipsis_args": false, "name": "root of QuickUnionFirstImprovement", "ret_type": "builtins.int", "variables": []}}}, "root_ids": {".class": "SymbolTableNode", "implicit": true, "kind": "Mdef", "node": {".class": "Var", "flags": [], "fullname": "datastructure.graph.union_find.QuickUnionFirstImprovement.root_ids", "name": "root_ids", "type": {".class": "Instance", "args": ["builtins.int"], "type_ref": "builtins.list"}}}, "sz": {".class": "SymbolTableNode", "implicit": true, "kind": "Mdef", "node": {".class": "Var", "flags": [], "fullname": "datastructure.graph.union_find.QuickUnionFirstImprovement.sz", "name": "sz", "type": {".class": "Instance", "args": ["builtins.int"], "type_ref": "builtins.list"}}}, "union": {".class": "SymbolTableNode", "kind": "Mdef", "node": {".class": "FuncDef", "arg_kinds": [0, 0, 0], "arg_names": ["self", "p", "q"], "flags": [], "fullname": "datastructure.graph.union_find.QuickUnionFirstImprovement.union", "name": "union", "type": {".class": "CallableType", "arg_kinds": [0, 0, 0], "arg_names": ["self", "p", "q"], "arg_types": ["datastructure.graph.union_find.QuickUnionFirstImprovement", "builtins.int", "builtins.int"], "bound_args": [], "def_extras": {"first_arg": "self"}, "fallback": "builtins.function", "implicit": false, "is_ellipsis_args": false, "name": "union of QuickUnionFirstImprovement", "ret_type": {".class": "NoneType"}, "variables": []}}}}, "tuple_type": null, "type_vars": [], "typeddict_type": null}}, "QuickUnionSecondImprovement": {".class": "SymbolTableNode", "kind": "Gdef", "node": {".class": "TypeInfo", "_promote": null, "abstract_attributes": [], "bases": ["builtins.object"], "declared_metaclass": null, "defn": {".class": "ClassDef", "fullname": "datastructure.graph.union_find.QuickUnionSecondImprovement", "name": "QuickUnionSecondImprovement", "type_vars": []}, "flags": [], "fullname": "datastructure.graph.union_find.QuickUnionSecondImprovement", "metaclass_type": null, "metadata": {}, "module_name": "datastructure.graph.union_find", "mro": ["datastructure.graph.union_find.QuickUnionSecondImprovement", "builtins.object"], "names": {".class": "SymbolTable", "__init__": {".class": "SymbolTableNode", "kind": "Mdef", "node": {".class": "FuncDef", "arg_kinds": [0, 0], "arg_names": ["self", "N"], "flags": [], "fullname": "datastructure.graph.union_find.QuickUnionSecondImprovement.__init__", "name": "__init__", "type": {".class": "CallableType", "arg_kinds": [0, 0], "arg_names": ["self", "N"], "arg_types": ["datastructure.graph.union_find.QuickUnionSecondImprovement", "builtins.int"], "bound_args": [], "def_extras": {"first_arg": "self"}, "fallback": "builtins.function", "implicit": false, "is_ellipsis_args": false, "name": "__init__ of QuickUnionSecondImprovement", "ret_type": {".class": "NoneType"}, "variables": []}}}, "find": {".class": "SymbolTableNode", "kind": "Mdef", "node": {".class": "FuncDef", "arg_kinds": [0, 0, 0], "arg_names": ["self", "p", "q"], "flags": [], "fullname": "datastructure.graph.union_find.QuickUnionSecondImprovement.find", "name": "find", "type": {".class": "CallableType", "arg_kinds": [0, 0, 0], "arg_names": ["self", "p", "q"], "arg_types": ["datastructure.graph.union_find.QuickUnionSecondImprovement", "builtins.int", "builtins.int"], "bound_args": [], "def_extras": {"first_arg": "self"}, "fallback": "builtins.function", "implicit": false, "is_ellipsis_args": false, "name": "find of QuickUnionSecondImprovement", "ret_type": "builtins.bool", "variables": []}}}, "root": {".class": "SymbolTableNode", "kind": "Mdef", "node": {".class": "FuncDef", "arg_kinds": [0, 0], "arg_names": ["self", "i"], "flags": [], "fullname": "datastructure.graph.union_find.QuickUnionSecondImprovement.root", "name": "root", "type": {".class": "CallableType", "arg_kinds": [0, 0], "arg_names": ["self", "i"], "arg_types": ["datastructure.graph.union_find.QuickUnionSecondImprovement", "builtins.int"], "bound_args": [], "def_extras": {"first_arg": "self"}, "fallback": "builtins.function", "implicit": false, "is_ellipsis_args": false, "name": "root of QuickUnionSecondImprovement", "ret_type": "builtins.int", "variables": []}}}, "root_ids": {".class": "SymbolTableNode", "implicit": true, "kind": "Mdef", "node": {".class": "Var", "flags": [], "fullname": "datastructure.graph.union_find.QuickUnionSecondImprovement.root_ids", "name": "root_ids", "type": {".class": "Instance", "args": ["builtins.int"], "type_ref": "builtins.list"}}}, "sz": {".class": "SymbolTableNode", "implicit": true, "kind": "Mdef", "node": {".class": "Var", "flags": [], "fullname": "datastructure.graph.union_find.QuickUnionSecondImprovement.sz", "name": "sz", "type": {".class": "Instance", "args": ["builtins.int"], "type_ref": "builtins.list"}}}, "union": {".class": "SymbolTableNode", "kind": "Mdef", "node": {".class": "FuncDef", "arg_kinds": [0, 0, 0], "arg_names": ["self", "p", "q"], "flags": [], "fullname": "datastructure.graph.union_find.QuickUnionSecondImprovement.union", "name": "union", "type": {".class": "CallableType", "arg_kinds": [0, 0, 0], "arg_names": ["self", "p", "q"], "arg_types": ["datastructure.graph.union_find.QuickUnionSecondImprovement", "builtins.int", "builtins.int"], "bound_args": [], "def_extras": {"first_arg": "self"}, "fallback": "builtins.function", "implicit": false, "is_ellipsis_args": false, "name": "union of QuickUnionSecondImprovement", "ret_type": {".class": "NoneType"}, "variables": []}}}}, "tuple_type": null, "type_vars": [], "typeddict_type": null}}, "__doc__": {".class": "SymbolTableNode", "kind": "Gdef", "node": {".class": "Var", "flags": ["is_ready"], "fullname": "datastructure.graph.union_find.__doc__", "name": "__doc__", "type": "builtins.str"}}, "__file__": {".class": "SymbolTableNode", "kind": "Gdef", "node": {".class": "Var", "flags": ["is_ready"], "fullname": "datastructure.graph.union_find.__file__", "name": "__file__", "type": "builtins.str"}}, "__name__": {".class": "SymbolTableNode", "kind": "Gdef", "node": {".class": "Var", "flags": ["is_ready"], "fullname": "datastructure.graph.union_find.__name__", "name": "__name__", "type": "builtins.str"}}, "__package__": {".class": "SymbolTableNode", "kind": "Gdef", "node": {".class": "Var", "flags": ["is_ready"], "fullname": "datastructure.graph.union_find.__package__", "name": "__package__", "type": "builtins.str"}}}, "path": "./datastructure/graph/union_find.py"}